[
  {
    "id": 0,
    "name": "Constraint Layout",
    "description": "Description about Constraint Layout.",
    "img": "https://i.wpimg.pl/O/644x429/d.wpimg.pl/2148438399-1788913762/wegiel.jpg"
  },
  {
    "id": 1,
    "name": "Intent data passin",
    "description": "Description about data passing.",
    "img": "https://i.wpimg.pl/O/644x429/d.wpimg.pl/2148438399-1788913762/wegiel.jpg"
  },
  {
    "id": 2,
    "name": "Fragments",
    "description": "Description about fragments.",
    "img": "https://i.wpimg.pl/O/644x429/d.wpimg.pl/2148438399-1788913762/wegiel.jpg"
  },
  {
    "id": 3,
    "name": "Dialogs",
    "description": "Description about dialogs.",
    "img": "https://i.wpimg.pl/O/644x429/d.wpimg.pl/2148438399-1788913762/wegiel.jpg"
  },
  {
    "id": 4,
    "name": "BottomNavigation",
    "description": "Description about BottomNavigation.",
    "img": "https://i.wpimg.pl/O/644x429/d.wpimg.pl/2148438399-1788913762/wegiel.jpg"
  },
  {
    "id": 5,
    "name": "BottomSheetFragment",
    "description": "Description about BottomSheetFragment.",
    "img": "https://i.wpimg.pl/O/644x429/d.wpimg.pl/2148438399-1788913762/wegiel.jpg"
  },
  {
    "id": 6,
    "name": "GoogleMaps",
    "description": "Description about GoogleMaps.",
    "img": "https://i.wpimg.pl/O/644x429/d.wpimg.pl/2148438399-1788913762/wegiel.jpg"
  },
  {
    "id": 7,
    "name": "Taking photos",
    "description": "Description about taking photos.",
    "img": "https://i.wpimg.pl/O/644x429/d.wpimg.pl/2148438399-1788913762/wegiel.jpg"
  },
  {
    "id": 8,
    "name": "QR Code scanner",
    "description": "Description about QR Code scanner.",
    "img": "https://i.wpimg.pl/O/644x429/d.wpimg.pl/2148438399-1788913762/wegiel.jpg"
  }
]